headsup.py
headsup_fast-1.0.0.dist-info/licenses/LICENSE
headsup_fast-1.0.0.dist-info/METADATA
headsup_fast-1.0.0.dist-info/WHEEL
headsup_fast-1.0.0.dist-info/entry_points.txt
headsup_fast-1.0.0.dist-info/top_level.txt
headsup_fast-1.0.0.dist-info/RECORD
