Metadata-Version: 2.4
Name: headsup-fast
Version: 1.0.0
Summary: A trivial alternative to Ubuntu's landscape-info with no external dependencies
Home-page: https://github.com/ahmadalam/headsup-fast
Author: Ahmad Alam
Author-email: Ahmad Alam <ahmadalam@outlook.com>
Project-URL: Homepage, https://github.com/ahmadalam/headsup-fast
Project-URL: Bug Reports, https://github.com/ahmadalam/headsup-fast/issues
Project-URL: Source, https://github.com/ahmadalam/headsup-fast
Keywords: system,monitoring,motd,landscape,ubuntu,linux,sysinfo
Classifier: Development Status :: 5 - Production/Stable
Classifier: Intended Audience :: System Administrators
Classifier: License :: OSI Approved :: MIT License
Classifier: Operating System :: POSIX :: Linux
Classifier: Programming Language :: Python :: 3
Classifier: Programming Language :: Python :: 3.6
Classifier: Programming Language :: Python :: 3.7
Classifier: Programming Language :: Python :: 3.8
Classifier: Programming Language :: Python :: 3.9
Classifier: Programming Language :: Python :: 3.10
Classifier: Programming Language :: Python :: 3.11
Classifier: Programming Language :: Python :: 3.12
Classifier: Topic :: System :: Systems Administration
Classifier: Topic :: System :: Monitoring
Requires-Python: >=3.6
License-File: LICENSE
Dynamic: author
Dynamic: home-page
Dynamic: license-file
Dynamic: requires-python
